{
  "title": "title.dwm.ars.structure.room_wooden_huge_bamboo",
  "structure": "dwm:tardis/ars/rooms/_/huge",
  "replaces": {
    "minecraft:blue_concrete": "minecraft:stripped_dark_oak_wood",
    "minecraft:white_concrete": "minecraft:bamboo_mosaic",
    "minecraft:black_concrete": "minecraft:bamboo_block",
    "minecraft:gray_concrete": "minecraft:bamboo_block",
    "minecraft:brown_concrete": "minecraft:bamboo_block",
    "minecraft:light_gray_concrete": "minecraft:bamboo_block",
    "minecraft:andesite_stairs": "minecraft:bamboo_stairs",
    "minecraft:diorite_stairs": "minecraft:bamboo_stairs",
    "minecraft:stone_stairs": "minecraft:bamboo_stairs",
    "minecraft:stone_slab": "minecraft:bamboo_slab",
    "minecraft:glass_pane": "minecraft:light_blue_stained_glass_pane",
    "minecraft:andesite_wall": "minecraft:bamboo_fence",
    "minecraft:diorite_wall": "minecraft:bamboo_fence"
  }
}
