{
  "title": "title.dwm.ars.structure.hallway_wooden_turn_right_short_birch",
  "structure": "dwm:tardis/ars/hallways/_/turn_right_short",
  "replaces": {
    "minecraft:blue_concrete": "minecraft:stripped_spruce_wood",
    "minecraft:white_concrete": "minecraft:stripped_birch_wood",
    "minecraft:black_concrete": "minecraft:birch_wood",
    "minecraft:gray_concrete": "minecraft:birch_planks",
    "minecraft:brown_concrete": "minecraft:birch_planks",
    "minecraft:light_gray_concrete": "minecraft:birch_log",
    "minecraft:andesite_stairs": "minecraft:birch_stairs",
    "minecraft:diorite_stairs": "minecraft:birch_stairs",
    "minecraft:stone_stairs": "minecraft:birch_stairs",
    "minecraft:stone_slab": "minecraft:birch_slab",
    "minecraft:glass_pane": "minecraft:light_blue_stained_glass_pane"
  }
}
